Workbook

Sheet Peg
A1: THE PEG — change B2 and every tab recomputes
A2: Coins per ₹1 of discount value | B2: 10
A4: Yellow cells are inputs I own and must defend. Green cells are computed.
A5: Referenced everywhere as Peg!$B$2 — never restate the peg in another cell.

Sheet Earn
A1: EARN RATES
A3: Event | B3: Coins
A4: Match win | B4: 50
A5: Match loss | B5: 15
A6: Daily streak | B6: 40
A7: Assumed win rate | B7: 0.5
A9: Archetype | B9: Matches/day | C9: Days played /wk | D9: Share of DAU | E9: Coins/day | F9: Coins/week | G9: 48h budget | H9: 3-week budget
A10: Grinder | B10: 15 | C10: 7 | D10: 0.25 | E10: =B10*($B$4*$B$7+$B$5*(1-$B$7))+$B$6*(C10/7) | F10: =E10*7 | G10: =E10*2 | H10: =E10*21
A11: Dipper | B11: 1.43 | C11: 2.5 | D11: 0.6 | E11: =B11*($B$4*$B$7+$B$5*(1-$B$7))+$B$6*(C11/7) | F11: =E11*7 | G11: =E11*2 | H11: =E11*21
A12: Whale | B12: 6 | C12: 7 | D12: 0.15 | E12: =B12*($B$4*$B$7+$B$5*(1-$B$7))+$B$6*(C12/7) | F12: =E12*7 | G12: =E12*2 | H12: =E12*21
A14: Blended platform coins/day | B14: =SUMPRODUCT(E10:E12,D10:D12)

Sheet Catalog
A1: CATALOG — coins = MRP × cap × peg. Cash = MRP − coins/peg.
A3: # | B3: SKU | C3: Type | D3: MRP ₹ | E3: Coin cap | F3: Coins | G3: Cash ₹ | H3: Days: Grinder | I3: Days: Dipper | J3: Days: Whale
A4: 1 | B4: Zepto ₹10 off ₹99 | C4: voucher | D4: 10 | E4: 1 | F4: =D4*E4*Peg!$B$2 | G4: =D4-F4/Peg!$B$2 | H4: =F4/Earn!$E$10 | I4: =F4/Earn!$E$11 | J4: =F4/Earn!$E$12
A5: 2 | B5: Swiggy ₹40 off ₹149 | C5: voucher | D5: 40 | E5: 1 | F5: =D5*E5*Peg!$B$2 | G5: =D5-F5/Peg!$B$2 | H5: =F5/Earn!$E$10 | I5: =F5/Earn!$E$11 | J5: =F5/Earn!$E$12
A6: 3 | B6: Zomato ₹50 off ₹199 | C6: voucher | D6: 50 | E6: 1 | F6: =D6*E6*Peg!$B$2 | G6: =D6-F6/Peg!$B$2 | H6: =F6/Earn!$E$10 | I6: =F6/Earn!$E$11 | J6: =F6/Earn!$E$12
A7: 4 | B7: Starbucks ₹100 off ₹299 | C7: voucher | D7: 100 | E7: 1 | F7: =D7*E7*Peg!$B$2 | G7: =D7-F7/Peg!$B$2 | H7: =F7/Earn!$E$10 | I7: =F7/Earn!$E$11 | J7: =F7/Earn!$E$12
A8: 5 | B8: PharmEasy ₹200 off ₹799 | C8: voucher | D8: 200 | E8: 1 | F8: =D8*E8*Peg!$B$2 | G8: =D8-F8/Peg!$B$2 | H8: =F8/Earn!$E$10 | I8: =F8/Earn!$E$11 | J8: =F8/Earn!$E$12
A9: 6 | B9: Decathlon ₹300 off ₹999 | C9: voucher | D9: 300 | E9: 1 | F9: =D9*E9*Peg!$B$2 | G9: =D9-F9/Peg!$B$2 | H9: =F9/Earn!$E$10 | I9: =F9/Earn!$E$11 | J9: =F9/Earn!$E$12
A10: 7 | B10: Spotify Premium 1mo | C10: product·digital | D10: 139 | E10: 0.4 | F10: =D10*E10*Peg!$B$2 | G10: =D10-F10/Peg!$B$2 | H10: =F10/Earn!$E$10 | I10: =F10/Earn!$E$11 | J10: =F10/Earn!$E$12
A11: 8 | B11: Netflix Mobile 1mo | C11: product·digital | D11: 149 | E11: 0.4 | F11: =D11*E11*Peg!$B$2 | G11: =D11-F11/Peg!$B$2 | H11: =F11/Earn!$E$10 | I11: =F11/Earn!$E$11 | J11: =F11/Earn!$E$12
A12: 9 | B12: JioHotstar Super 1yr | C12: product·digital | D12: 1499 | E12: 0.4 | F12: =D12*E12*Peg!$B$2 | G12: =D12-F12/Peg!$B$2 | H12: =F12/Earn!$E$10 | I12: =F12/Earn!$E$11 | J12: =F12/Earn!$E$12
A13: 10 | B13: boAt Airdopes 141 | C13: product·physical | D13: 1299 | E13: 0.4 | F13: =D13*E13*Peg!$B$2 | G13: =D13-F13/Peg!$B$2 | H13: =F13/Earn!$E$10 | I13: =F13/Earn!$E$11 | J13: =F13/Earn!$E$12
A14: 11 | B14: Puma Softride sliders | C14: product·physical | D14: 1499 | E14: 0.4 | F14: =D14*E14*Peg!$B$2 | G14: =D14-F14/Peg!$B$2 | H14: =F14/Earn!$E$10 | I14: =F14/Earn!$E$11 | J14: =F14/Earn!$E$12
A15: 12 | B15: Sony WH-CH520 | C15: product·physical | D15: 2999 | E15: 0.4 | F15: =D15*E15*Peg!$B$2 | G15: =D15-F15/Peg!$B$2 | H15: =F15/Earn!$E$10 | I15: =F15/Earn!$E$11 | J15: =F15/Earn!$E$12
B17: REACHABILITY TEST
B18: Test: something reachable inside 2 days, something aspirational at 2-4 weeks.
B19: Archetype | C19: Cheapest SKU | D19: Days | E19: Aspiration SKU | F19: Days | G19: Pass?
B20: Grinder | C20: =B7 | D20: =H7 | E20: =B15 | F20: =H15 | G20: =IF(AND(D20<=2,F20>=14,F20<=28),"PASS","FAIL")
B21: Dipper | C21: =B4 | D21: =I4 | E21: =B7 | F21: =I7 | G21: =IF(AND(D21<=2,F21>=14,F21<=28),"PASS","FAIL")
B22: Whale | C22: =B5 | D22: =J5 | E22: =B13 | F22: =J13 | G22: =IF(AND(D22<=2,F22>=14,F22<=28),"PASS","FAIL")

Sheet Guardrails
A1: GUARDRAILS
A3: Guardrail | B3: Value | C3: Protects
A4: Redemptions / player / week | B4: 2 | C4: Brand CAC budget + coupon inventory — the real control
A5: Daily coin earn ceiling | B5: 900 | C5: Farming. ~1.7x a Grinder's normal day: binds bots, not humans
A6: Voucher non-redemption rate | B6: 0.15 | C6: Assumed. Drives the coin-refund float below
A7: Whale IAP ARPDAU kill threshold | B7: -0.02 | C7: The thing this store was sold to protect
A9: MINT VS SINK PER ARCHETYPE
A10: Archetype | B10: Mint/week | C10: Max sink/week | D10: Net | E10: Verdict
A11: Grinder | B11: =Earn!$F$10 | C11: =Catalog!$F$8*$B$4 | D11: =B11-C11 | E11: =IF(D11>0,"Mints faster than it sinks — needs a higher tier","Can sink faster than it mints — healthy")
A12: Dipper | B12: =Earn!$F$11 | C12: =Catalog!$F$5*$B$4 | D12: =B12-C12 | E12: =IF(D12>0,"Mints faster than it sinks — needs a higher tier","Can sink faster than it mints — healthy")
A13: Whale | B13: =Earn!$F$12 | C13: =Catalog!$F$6*$B$4 | D13: =B13-C13 | E13: =IF(D13>0,"Mints faster than it sinks — needs a higher tier","Can sink faster than it mints — healthy")
A16: Coins refunded/week from expiry | B16: =SUM(C11:C13)*B6

Sheet UnitEconomics
A1: UNIT ECONOMICS — the redemption rate is DERIVED from PlaySuper's published +5.2% ARPDAU, not guessed
A3: Line | B3: Value | C3: Source / formula
A4: DAU | B4: 1000000 | C4: input
A5: Baseline ARPDAU | B5: 0.8 | C5: input
A6: Target ARPDAU lift | B6: 0.052 | C6: PlaySuper published figure
A7: Incremental revenue / DAU / day | B7: =B5*B6 | C7: computed
A8: Average order value at redemption | B8: 700 | C8: input — I own this
A9: PlaySuper commission % | B9: 0.1 | C9: input — I own this
A10: PlaySuper commission ₹ | B10: =B8*B9 | C10: computed
A11: Studio share of commission % | B11: 0.5 | C11: input — I own this
A12: Studio revenue per redemption ₹ | B12: =B10*B11 | C12: computed
A13: IMPLIED daily redemption rate | B13: =B7/B12 | C13: incremental ÷ studio rev per redemption
A14: Redemptions / day | B14: =B4*B13 | C14: computed
A15: Redemptions / month | B15: =B14*30 | C15: computed
A16: Average discount funded by brand ₹ | B16: 150 | C16: input — I own this
A17: BRAND CAC BUDGET REQUIRED / month | B17: =B15*B16 | C17: the real ceiling
A18: Share of DAU redeeming per month | B18: =B15/B4 | C18: computed
A19: Redemption cap headroom (cap 8/mo) | B19: =8/(B18*30/30) | C19: cap ÷ modal monthly redemptions
A23: CONCLUSION 1
A24: Only ~0.12% of DAU — about 1 player in 840 — need to redeem daily to hit the published ARPDAU lift. So optimise for RETENTION BREADTH (many players holding a reserved Goal), not CONVERSION DEPTH (many checkouts). A held Goal costs the brand nothing and returns a player tomorrow; a checkout costs CAC and may not.
A26: CONCLUSION 2
A27: The monthly brand CAC budget is the real ceiling — not studio cost. If brands fund less, the redemption cap tightens or the average discount drops. The coin faucet does not move. Faucet and budget are INDEPENDENT levers.

Sheet Values
A1: VALUES — hardcoded duplicate of every computed figure.
A2: openpyxl writes formulas with no cached result, so Apple Numbers / Quick Look render those cells blank until the file is opened in Excel. This tab guarantees the model is readable anywhere. If it disagrees with the formula tabs, the formula tabs win.
A4: PEG (coins per ₹1) | B4: 10
A6: COINS/DAY | B6: Grinder | C6: Dipper | D6: Whale
B7: 528 | C7: 61 | D7: 235
A8: 48h budget | B8: 1055 | C8: 122 | D8: 470
A9: 3-week budget | B9: 11078 | C9: 1276 | D9: 4935
A11: UNIT ECONOMICS
A12: Incremental rev / DAU / day | B12: ₹0.0416
A13: Studio rev per redemption | B13: ₹35
A14: Implied daily redemption rate | B14: 0.119%
A15: Redemptions / day @ 1M DAU | B15: 1,189
A16: Redemptions / month | B16: 35,657
A17: Brand CAC budget / month | B17: ₹5,348,571
A18: Share of DAU redeeming / month | B18: 3.6%
A21: CATALOG (computed)
A22: SKU | B22: Coins | C22: Cash ₹ | D22: Days: Grinder | E22: Days: Dipper | F22: Days: Whale
A23: Zepto ₹10 off ₹99 | B23: 100 | C23: 0 | D23: 0.2 | E23: 1.6 | F23: 0.4
A24: Swiggy ₹40 off ₹149 | B24: 400 | C24: 0 | D24: 0.8 | E24: 6.6 | F24: 1.7
A25: Zomato ₹50 off ₹199 | B25: 500 | C25: 0 | D25: 0.9 | E25: 8.2 | F25: 2.1
A26: Starbucks ₹100 off ₹299 | B26: 1000 | C26: 0 | D26: 1.9 | E26: 16.5 | F26: 4.3
A27: PharmEasy ₹200 off ₹799 | B27: 2000 | C27: 0 | D27: 3.8 | E27: 32.9 | F27: 8.5
A28: Decathlon ₹300 off ₹999 | B28: 3000 | C28: 0 | D28: 5.7 | E28: 49.4 | F28: 12.8
A29: Spotify Premium 1mo | B29: 556 | C29: 83 | D29: 1.1 | E29: 9.2 | F29: 2.4
A30: Netflix Mobile 1mo | B30: 596 | C30: 89 | D30: 1.1 | E30: 9.8 | F30: 2.5
A31: JioHotstar Super 1yr | B31: 5996 | C31: 899 | D31: 11.4 | E31: 98.7 | F31: 25.5
A32: boAt Airdopes 141 | B32: 5196 | C32: 779 | D32: 9.9 | E32: 85.5 | F32: 22.1
A33: Puma Softride sliders | B33: 5996 | C33: 899 | D33: 11.4 | E33: 98.7 | F33: 25.5
A34: Sony WH-CH520 | B34: 11996 | C34: 1799 | D34: 22.7 | E34: 197.4 | F34: 51
